LICENSE
README.md
setup.cfg
setup.py
arcache/ImageTK.py
arcache/__init__.py
arcache/cache.py
arcache/defaults.ini
arcache/err.png
arcache.egg-info/PKG-INFO
arcache.egg-info/SOURCES.txt
arcache.egg-info/dependency_links.txt
arcache.egg-info/requires.txt
arcache.egg-info/top_level.txt