Metadata-Version: 2.1
Name: arcache
Version: 0.1
Summary: LRU Cache for TKInter using PIL
Home-page: https://github.com/manbehindthemadness/rcache
Author: manbehindthemadness
Author-email: manbehindthemadness@gmail.com
License: MIT
Keywords: tkinter,pil,cache
Platform: UNKNOWN
License-File: LICENSE
